nag/__init__.py
nag/cli.py
nag/core.py
nag/db.py
nag/helpers.py
nag-0.3.0b1.dist-info/LICENSE
nag-0.3.0b1.dist-info/METADATA
nag-0.3.0b1.dist-info/WHEEL
nag-0.3.0b1.dist-info/entry_points.txt
nag-0.3.0b1.dist-info/RECORD
