Metadata-Version: 2.1
Name: nag
Version: 0.3.0b1
Summary: A command line time blocker that nags you to get things done
Home-page: https://github.com/ykumards/nag
License: MIT
Keywords: productivity,time management,nag,CLI,time blocker
Author: Yogesh Kumar
Author-email: ykumards@gmail.com
Requires-Python: >=3.11,<4.0
Classifier: License :: OSI Approved :: MIT License
Classifier: Programming Language :: Python :: 3
Classifier: Programming Language :: Python :: 3.11
Classifier: Programming Language :: Python :: 3.12
Requires-Dist: bump2version (>=1.0.1,<2.0.0)
Requires-Dist: click (>=8.1.7,<9.0.0)
Requires-Dist: pyyaml (>=6.0.2,<7.0.0)
Requires-Dist: rich (>=13.8.1,<14.0.0)
Requires-Dist: sqlalchemy (>=2.0.35,<3.0.0)
Requires-Dist: sqlite-vec (>=0.1.2,<0.2.0)
Project-URL: Repository, https://github.com/ykumards/nag
